README.md
setup.cfg
setup.py
pygtfs/__init__.py
pygtfs/exceptions.py
pygtfs/feed.py
pygtfs/gtfs2db.py
pygtfs/gtfs_entities.py
pygtfs/loader.py
pygtfs/schedule.py
pygtfs/test/__init__.py
pygtfs/test/test.py
pygtfs_homeassistant.egg-info/PKG-INFO
pygtfs_homeassistant.egg-info/SOURCES.txt
pygtfs_homeassistant.egg-info/dependency_links.txt
pygtfs_homeassistant.egg-info/entry_points.txt
pygtfs_homeassistant.egg-info/requires.txt
pygtfs_homeassistant.egg-info/top_level.txt