Metadata-Version: 1.1
Name: pygtfs-homeassistant
Version: 0.1.3.dev0
Summary: Models GTFS data in a database.
Home-page: https://github.com/jarondl/pygtfs
Author: Yaron de Leeuw
Author-email: me@jarondl.net
License: MIT
Keywords: gtfs
Platform: UNKNOWN
Classifier: Operating System :: OS Independent
Classifier: License :: OSI Approved :: MIT License
Classifier: Programming Language :: Python :: 2
Classifier: Programming Language :: Python :: 2.6
Classifier: Programming Language :: Python :: 2.7
Classifier: Programming Language :: Python :: 3
Classifier: Programming Language :: Python :: 3.2
Classifier: Programming Language :: Python :: 3.3
Classifier: Programming Language :: Python :: 3.4
Classifier: Programming Language :: Python :: 3.5
